Workbook

Sheet Broadcast Ad Sales Log
A1: Club Name | B1: Metro United SC
A2: Broadcaster (TV) | B2: Sports Network 7 (SN7)
A3: Broadcaster (Radio) | B3: KMTX AM 850
A4: Game | B4: Metro United SC vs. Riverside City FC
A5: Game Date | B5: TBD, 202x
A6: Venue | B6: Metro Arena, Chicago, IL
A7: Currency | B7: USD ($)
A8: Report Prepared By | B8: Broadcast Partnerships Dept
A9: Submission Date | B9: 202x
A11: Log ID | B11: Medium | C11: Channel / Station | D11: Game Period | E11: On-Air Date | F11: On-Air Start Time | G11: Duration (Seconds) | H11: Ad / Slot Type | I11: Sponsor / Advertiser | J11: # Spots / Mentions | K11: Rate Card ($/unit) | L11: Actual Rate ($/unit) | M11: Gross Revenue ($) | N11: Broadcaster Comm % | O11: Broadcaster Comm ($) | P11: Net Revenue to Club ($)
A12: LOG-001 | B12: TV | C12: SN7 | D12: Pre-Game | E12: 202x | F12: 10:00 AM | G12: 30 | H12: Commercial Spot | I12: AutoNation | J12: 2 | K12: 4200 | L12: 4200 | M12: =J12*L12 -> 8400 | N12: 0.2 | O12: =M12*N12 -> 1680 | P12: =M12-O12 -> 6720
A13: LOG-002 | B13: TV | C13: SN7 | D13: Pre-Game | E13: 202x | F13: 10:05 AM | G13: 30 | H13: Commercial Spot | I13: State Farm | J13: 2 | K13: 4200 | L13: 3900 | M13: =J13*L13 -> 7800 | N13: 0.2 | O13: =M13*N13 -> 1560 | P13: =M13-O13 -> 6240
A14: LOG-003 | B14: TV | C14: SN7 | D14: Pre-Game | E14: 202x | F14: 10:08 AM | G14: 60 | H14: Sponsored Segment | I14: Gatorade – Pre-Game Show | J14: 1 | K14: 8500 | L14: 8500 | M14: =J14*L14 -> 8500 | N14: 0.2 | O14: =M14*N14 -> 1700 | P14: =M14-O14 -> 6800
A15: LOG-004 | B15: TV | C15: SN7 | D15: Pre-Game | E15: 202x | F15: 10:12 AM | G15: 15 | H15: Billboard Read | I15: Nike | J15: 1 | K15: 1800 | L15: 1800 | M15: =J15*L15 -> 1800 | N15: 0.2 | O15: =M15*N15 -> 360 | P15: =M15-O15 -> 1440
A16: LOG-005 | B16: TV | C16: SN7 | D16: Pre-Game | E16: 202x | F16: 10:15 AM | G16: 30 | H16: Player Mention | I16: Verizon – feat. A. Rivera #10 | J16: 1 | K16: 5500 | L16: 5500 | M16: =J16*L16 -> 5500 | N16: 0.2 | O16: =M16*N16 -> 1100 | P16: =M16-O16 -> 4400
A17: LOG-006 | B17: TV | C17: SN7 | D17: 1st Half | E17: 202x | F17: 11:02 AM | G17: 30 | H17: Commercial Spot | I17: Pepsi | J17: 2 | K17: 5800 | L17: 5800 | M17: =J17*L17 -> 11600 | N17: 0.2 | O17: =M17*N17 -> 2320 | P17: =M17-O17 -> 9280
A18: LOG-007 | B18: TV | C18: SN7 | D18: 1st Half | E18: 202x | F18: 11:20 AM | G18: 30 | H18: Commercial Spot | I18: Chevrolet | J18: 2 | K18: 5800 | L18: 5500 | M18: =J18*L18 -> 11000 | N18: 0.2 | O18: =M18*N18 -> 2200 | P18: =M18-O18 -> 8800
A19: LOG-008 | B19: TV | C19: SN7 | D19: 1st Half | E19: 202x | F19: 11:25 AM | G19: 15 | H19: Replay Sponsor | I19: Verizon – Instant Replay | J19: 3 | K19: 2200 | L19: 2200 | M19: =J19*L19 -> 6600 | N19: 0.2 | O19: =M19*N19 -> 1320 | P19: =M19-O19 -> 5280
A20: LOG-009 | B20: TV | C20: SN7 | D20: 1st Half | E20: 202x | F20: 11:33 AM | G20: 30 | H20: Player Mention | I20: State Farm – feat. J. Thompson #7 | J20: 1 | K20: 6200 | L20: 6200 | M20: =J20*L20 -> 6200 | N20: 0.2 | O20: =M20*N20 -> 1240 | P20: =M20-O20 -> 4960
A21: LOG-010 | B21: TV | C21: SN7 | D21: 1st Half | E21: 202x | F21: 11:40 AM | G21: 60 | H21: Injury Timeout Spot | I21: Geico | J21: 1 | K21: 7000 | L21: 6500 | M21: =J21*L21 -> 6500 | N21: 0.2 | O21: =M21*N21 -> 1300 | P21: =M21-O21 -> 5200
A22: LOG-011 | B22: TV | C22: SN7 | D22: Halftime | E22: 202x | F22: 12:00 PM | G22: 300 | H22: Halftime Show Presenting | I22: Bud Light | J22: 1 | K22: 22000 | L22: 22000 | M22: =J22*L22 -> 22000 | N22: 0.2 | O22: =M22*N22 -> 4400 | P22: =M22-O22 -> 17600
A23: LOG-012 | B23: TV | C23: SN7 | D23: Halftime | E23: 202x | F23: 12:05 PM | G23: 30 | H23: Commercial Spot | I23: AutoNation | J23: 2 | K23: 4200 | L23: 4200 | M23: =J23*L23 -> 8400 | N23: 0.2 | O23: =M23*N23 -> 1680 | P23: =M23-O23 -> 6720
... A44: LOG-033 | B44: Radio | C44: KMTX AM 850 | D44: Post-Game | E44: 202x | F44: 2:09 PM | G44: 30 | H44: Live Read | I44: Papa Johns | J44: 1 | K44: 1500 | L44: 1400 | M44: =J44*L44 -> 1400 | N44: 0.15 | O44: =M44*N44 -> 210 | P44: =M44-O44 -> 1190
A45: TOTAL | J45: =SUM(J12:J44) -> 51 | M45: =SUM(M12:M44) -> 216900 | O45: =SUM(O12:O44) -> 42225 | P45: =SUM(P12:P44) -> 174675
A46: TV (SN7) Sub-Total | J46: =J12+J13+J14+J15+J16+J17+J18+J19+J20+J21+J22+J23+J24+J25+J26+J27+J28+J29+J30+J31+J32+J33+J34 -> 36 | M46: =M12+M13+M14+M15+M16+M17+M18+M19+M20+M21+M22+M23+M24+M25+M26+M27+M28+M29+M30+M31+M32+M33+M34 -> 193800 | O46: =O12+O13+O14+O15+O16+O17+O18+O19+O20+O21+O22+O23+O24+O25+O26+O27+O28+O29+O30+O31+O32+O33+O34 -> 38760 | P46: =P12+P13+P14+P15+P16+P17+P18+P19+P20+P21+P22+P23+P24+P25+P26+P27+P28+P29+P30+P31+P32+P33+P34 -> 155040
A47: Radio (KMTX AM 850) Sub-Total | J47: =J35+J36+J37+J38+J39+J40+J41+J42+J43+J44 -> 15 | M47: =M35+M36+M37+M38+M39+M40+M41+M42+M43+M44 -> 23100 | O47: =O35+O36+O37+O38+O39+O40+O41+O42+O43+O44 -> 3465 | P47: =P35+P36+P37+P38+P39+P40+P41+P42+P43+P44 -> 19635

Sheet Revenue by Sponsor Summary
A1: Club | B1: Metro United SC
A2: Game | B2: Metro United SC vs. Riverside City FC
A3: Period | B3: Single Game – 202x
A4: Purpose | B4: Billing verification & revenue recording by sponsor
A6: Sponsor / Advertiser | B6: Ad Type(s) | C6: Total Spots/Mentions | D6: Gross Revenue ($) | E6: Broadcaster Comm ($) | F6: Net Revenue to Club ($) | G6: Player Mention Royalty % | H6: League Revenue Share % | I6: Music/IP Royalty % | J6: Total Deductions % | K6: Player Mention Royalty ($) | L6: League Share ($) | M6: Music/IP Royalty ($) | N6: Club Net Revenue ($)
A7: AutoNation | B7: Commercial Spot | C7: ='Broadcast Ad Sales Log'!J12+'Broadcast Ad Sales Log'!J23+'Broadcast Ad Sales Log'!J32+'Broadcast Ad Sales Log'!J35+'Broadcast Ad Sales Log'!J43 -> 10 | D7: ='Broadcast Ad Sales Log'!M12+'Broadcast Ad Sales Log'!M23+'Broadcast Ad Sales Log'!M32+'Broadcast Ad Sales Log'!M35+'Broadcast Ad Sales Log'!M43 -> 30000 | E7: ='Broadcast Ad Sales Log'!O12+'Broadcast Ad Sales Log'!O23+'Broadcast Ad Sales Log'!O32+'Broadcast Ad Sales Log'!O35+'Broadcast Ad Sales Log'!O43 -> 5760 | F7: ='Broadcast Ad Sales Log'!P12+'Broadcast Ad Sales Log'!P23+'Broadcast Ad Sales Log'!P32+'Broadcast Ad Sales Log'!P35+'Broadcast Ad Sales Log'!P43 -> 24240 | G7: 0 | H7: 0.1 | I7: 0 | J7: =G7+H7+I7 -> 0.1 | K7: =F7*G7 -> 0 | L7: =F7*H7 -> 2424 | M7: =F7*I7 -> 0 | N7: =F7-K7-L7-M7 -> 21816
A8: State Farm | B8: Commercial Spot | C8: ='Broadcast Ad Sales Log'!J13 -> 2 | D8: ='Broadcast Ad Sales Log'!M13 -> 7800 | E8: ='Broadcast Ad Sales Log'!O13 -> 1560 | F8: ='Broadcast Ad Sales Log'!P13 -> 6240 | G8: 0 | H8: 0.1 | I8: 0 | J8: =G8+H8+I8 -> 0.1 | K8: =F8*G8 -> 0 | L8: =F8*H8 -> 624 | M8: =F8*I8 -> 0 | N8: =F8-K8-L8-M8 -> 5616
A9: Gatorade – Pre-Game Show | B9: Sponsored Segment | C9: ='Broadcast Ad Sales Log'!J14 -> 1 | D9: ='Broadcast Ad Sales Log'!M14 -> 8500 | E9: ='Broadcast Ad Sales Log'!O14 -> 1700 | F9: ='Broadcast Ad Sales Log'!P14 -> 6800 | G9: 0 | H9: 0.1 | I9: 0.02 | J9: =G9+H9+I9 -> 0.12 | K9: =F9*G9 -> 0 | L9: =F9*H9 -> 680 | M9: =F9*I9 -> 136 | N9: =F9-K9-L9-M9 -> 5984
A10: Nike | B10: Billboard Read | C10: ='Broadcast Ad Sales Log'!J15 -> 1 | D10: ='Broadcast Ad Sales Log'!M15 -> 1800 | E10: ='Broadcast Ad Sales Log'!O15 -> 360 | F10: ='Broadcast Ad Sales Log'!P15 -> 1440 | G10: 0 | H10: 0.1 | I10: 0 | J10: =G10+H10+I10 -> 0.1 | K10: =F10*G10 -> 0 | L10: =F10*H10 -> 144 | M10: =F10*I10 -> 0 | N10: =F10-K10-L10-M10 -> 1296
A11: Verizon – feat. A. Rivera #10 | B11: Player Mention | C11: ='Broadcast Ad Sales Log'!J16 -> 1 | D11: ='Broadcast Ad Sales Log'!M16 -> 5500 | E11: ='Broadcast Ad Sales Log'!O16 -> 1100 | F11: ='Broadcast Ad Sales Log'!P16 -> 4400 | G11: 0.08 | H11: 0.1 | I11: 0 | J11: =G11+H11+I11 -> 0.18 | K11: =F11*G11 -> 352 | L11: =F11*H11 -> 440 | M11: =F11*I11 -> 0 | N11: =F11-K11-L11-M11 -> 3608
A12: Pepsi | B12: Commercial Spot | C12: ='Broadcast Ad Sales Log'!J17+'Broadcast Ad Sales Log'!J27 -> 4 | D12: ='Broadcast Ad Sales Log'!M17+'Broadcast Ad Sales Log'!M27 -> 23200 | E12: ='Broadcast Ad Sales Log'!O17+'Broadcast Ad Sales Log'!O27 -> 4640 | F12: ='Broadcast Ad Sales Log'!P17+'Broadcast Ad Sales Log'!P27 -> 18560 | G12: 0 | H12: 0.1 | I12: 0 | J12: =G12+H12+I12 -> 0.1 | K12: =F12*G12 -> 0 | L12: =F12*H12 -> 1856 | M12: =F12*I12 -> 0 | N12: =F12-K12-L12-M12 -> 16704
A13: Chevrolet | B13: Commercial Spot | C13: ='Broadcast Ad Sales Log'!J18 -> 2 | D13: ='Broadcast Ad Sales Log'!M18 -> 11000 | E13: ='Broadcast Ad Sales Log'!O18 -> 2200 | F13: ='Broadcast Ad Sales Log'!P18 -> 8800 | G13: 0 | H13: 0.1 | I13: 0 | J13: =G13+H13+I13 -> 0.1 | K13: =F13*G13 -> 0 | L13: =F13*H13 -> 880 | M13: =F13*I13 -> 0 | N13: =F13-K13-L13-M13 -> 7920
A14: Verizon – Instant Replay | B14: Replay Sponsor | C14: ='Broadcast Ad Sales Log'!J19+'Broadcast Ad Sales Log'!J28 -> 6 | D14: ='Broadcast Ad Sales Log'!M19+'Broadcast Ad Sales Log'!M28 -> 13200 | E14: ='Broadcast Ad Sales Log'!O19+'Broadcast Ad Sales Log'!O28 -> 2640 | F14: ='Broadcast Ad Sales Log'!P19+'Broadcast Ad Sales Log'!P28 -> 10560 | G14: 0 | H14: 0.1 | I14: 0 | J14: =G14+H14+I14 -> 0.1 | K14: =F14*G14 -> 0 | L14: =F14*H14 -> 1056 | M14: =F14*I14 -> 0 | N14: =F14-K14-L14-M14 -> 9504
A15: State Farm – feat. J. Thompson #7 | B15: Player Mention | C15: ='Broadcast Ad Sales Log'!J20 -> 1 | D15: ='Broadcast Ad Sales Log'!M20 -> 6200 | E15: ='Broadcast Ad Sales Log'!O20 -> 1240 | F15: ='Broadcast Ad Sales Log'!P20 -> 4960 | G15: 0.08 | H15: 0.1 | I15: 0 | J15: =G15+H15+I15 -> 0.18 | K15: =F15*G15 -> 396.8 | L15: =F15*H15 -> 496 | M15: =F15*I15 -> 0 | N15: =F15-K15-L15-M15 -> 4067.2
A16: Geico | B16: Commercial Spot, Injury Timeout Spot | C16: ='Broadcast Ad Sales Log'!J21+'Broadcast Ad Sales Log'!J30+'Broadcast Ad Sales Log'!J40 -> 5 | D16: ='Broadcast Ad Sales Log'!M21+'Broadcast Ad Sales Log'!M30+'Broadcast Ad Sales Log'!M40 -> 20500 | E16: ='Broadcast Ad Sales Log'!O21+'Broadcast Ad Sales Log'!O30+'Broadcast Ad Sales Log'!O40 -> 3980 | F16: ='Broadcast Ad Sales Log'!P21+'Broadcast Ad Sales Log'!P30+'Broadcast Ad Sales Log'!P40 -> 16520 | G16: 0 | H16: 0.1 | I16: 0 | J16: =G16+H16+I16 -> 0.1 | K16: =F16*G16 -> 0 | L16: =F16*H16 -> 1652 | M16: =F16*I16 -> 0 | N16: =F16-K16-L16-M16 -> 14868
A17: Bud Light | B17: Halftime Show Presenting | C17: ='Broadcast Ad Sales Log'!J22 -> 1 | D17: ='Broadcast Ad Sales Log'!M22 -> 22000 | E17: ='Broadcast Ad Sales Log'!O22 -> 4400 | F17: ='Broadcast Ad Sales Log'!P22 -> 17600 | G17: 0 | H17: 0.1 | I17: 0.02 | J17: =G17+H17+I17 -> 0.12 | K17: =F17*G17 -> 0 | L17: =F17*H17 -> 1760 | M17: =F17*I17 -> 352 | N17: =F17-K17-L17-M17 -> 15488
A18: Papa Johns | B18: Commercial Spot, Live Read | C18: ='Broadcast Ad Sales Log'!J24+'Broadcast Ad Sales Log'!J37+'Broadcast Ad Sales Log'!J44 -> 5 | D18: ='Broadcast Ad Sales Log'!M24+'Broadcast Ad Sales Log'!M37+'Broadcast Ad Sales Log'!M44 -> 11600 | E18: ='Broadcast Ad Sales Log'!O24+'Broadcast Ad Sales Log'!O37+'Broadcast Ad Sales Log'!O44 -> 2140 | F18: ='Broadcast Ad Sales Log'!P24+'Broadcast Ad Sales Log'!P37+'Broadcast Ad Sales Log'!P44 -> 9460 | G18: 0 | H18: 0.1 | I18: 0 | J18: =G18+H18+I18 -> 0.1 | K18: =F18*G18 -> 0 | L18: =F18*H18 -> 946 | M18: =F18*I18 -> 0 | N18: =F18-K18-L18-M18 -> 8514
A19: Nike – feat. M. Osei #3 | B19: Player Mention | C19: ='Broadcast Ad Sales Log'!J25 -> 1 | D19: ='Broadcast Ad Sales Log'!M25 -> 6800 | E19: ='Broadcast Ad Sales Log'!O25 -> 1360 | F19: ='Broadcast Ad Sales Log'!P25 -> 5440 | G19: 0.08 | H19: 0.1 | I19: 0 | J19: =G19+H19+I19 -> 0.18 | K19: =F19*G19 -> 435.2 | L19: =F19*H19 -> 544 | M19: =F19*I19 -> 0 | N19: =F19-K19-L19-M19 -> 4460.8
A20: T-Mobile | B20: Commercial Spot | C20: ='Broadcast Ad Sales Log'!J26 -> 1 | D20: ='Broadcast Ad Sales Log'!M26 -> 7500 | E20: ='Broadcast Ad Sales Log'!O26 -> 1500 | F20: ='Broadcast Ad Sales Log'!P26 -> 6000 | G20: 0 | H20: 0.1 | I20: 0 | J20: =G20+H20+I20 -> 0.1 | K20: =F20*G20 -> 0 | L20: =F20*H20 -> 600 | M20: =F20*I20 -> 0 | N20: =F20-K20-L20-M20 -> 5400
A21: Gatorade – feat. A. Rivera #10 | B21: Player Mention | C21: ='Broadcast Ad Sales Log'!J29 -> 1 | D21: ='Broadcast Ad Sales Log'!M29 -> 6200 | E21: ='Broadcast Ad Sales Log'!O29 -> 1240 | F21: ='Broadcast Ad Sales Log'!P29 -> 4960 | G21: 0.08 | H21: 0.1 | I21: 0 | J21: =G21+H21+I21 -> 0.18 | K21: =F21*G21 -> 396.8 | L21: =F21*H21 -> 496 | M21: =F21*I21 -> 0 | N21: =F21-K21-L21-M21 -> 4067.2
A22: State Farm – Stat of the Game | B22: Sponsored Segment | C22: ='Broadcast Ad Sales Log'!J31 -> 1 | D22: ='Broadcast Ad Sales Log'!M31 -> 8500 | E22: ='Broadcast Ad Sales Log'!O31 -> 1700 | F22: ='Broadcast Ad Sales Log'!P31 -> 6800 | G22: 0 | H22: 0.1 | I22: 0 | J22: =G22+H22+I22 -> 0.1 | K22: =F22*G22 -> 0 | L22: =F22*H22 -> 680 | M22: =F22*I22 -> 0 | N22: =F22-K22-L22-M22 -> 6120
A23: Chevrolet – Post-Game Show | B23: Sponsored Segment | C23: ='Broadcast Ad Sales Log'!J33 -> 1 | D23: ='Broadcast Ad Sales Log'!M33 -> 8500 | E23: ='Broadcast Ad Sales Log'!O33 -> 1700 | F23: ='Broadcast Ad Sales Log'!P33 -> 6800 | G23: 0 | H23: 0.1 | I23: 0.02 | J23: =G23+H23+I23 -> 0.12 | K23: =F23*G23 -> 0 | L23: =F23*H23 -> 680 | M23: =F23*I23 -> 136 | N23: =F23-K23-L23-M23 -> 5984
A24: Nike – feat. J. Thompson #7 | B24: Player Mention | C24: ='Broadcast Ad Sales Log'!J34 -> 1 | D24: ='Broadcast Ad Sales Log'!M34 -> 5800 | E24: ='Broadcast Ad Sales Log'!O34 -> 1160 | F24: ='Broadcast Ad Sales Log'!P34 -> 4640 | G24: 0.08 | H24: 0.1 | I24: 0 | J24: =G24+H24+I24 -> 0.18 | K24: =F24*G24 -> 371.2 | L24: =F24*H24 -> 464 | M24: =F24*I24 -> 0 | N24: =F24-K24-L24-M24 -> 3804.8
A25: Subway | B25: Commercial Spot, Live Read | C25: ='Broadcast Ad Sales Log'!J36+'Broadcast Ad Sales Log'!J41 -> 3 | D25: ='Broadcast Ad Sales Log'!M36+'Broadcast Ad Sales Log'!M41 -> 3900 | E25: ='Broadcast Ad Sales Log'!O36+'Broadcast Ad Sales Log'!O41 -> 585 | F25: ='Broadcast Ad Sales Log'!P36+'Broadcast Ad Sales Log'!P41 -> 3315 | G25: 0 | H25: 0.1 | I25: 0 | J25: =G25+H25+I25 -> 0.1 | K25: =F25*G25 -> 0 | L25: =F25*H25 -> 331.5 | M25: =F25*I25 -> 0 | N25: =F25-K25-L25-M25 -> 2983.5
A26: State Farm – feat. A. Rivera #10 | B26: Player Mention | C26: ='Broadcast Ad Sales Log'!J38 -> 1 | D26: ='Broadcast Ad Sales Log'!M38 -> 2200 | E26: ='Broadcast Ad Sales Log'!O38 -> 330 | F26: ='Broadcast Ad Sales Log'!P38 -> 1870 | G26: 0.08 | H26: 0.1 | I26: 0 | J26: =G26+H26+I26 -> 0.18 | K26: =F26*G26 -> 149.6 | L26: =F26*H26 -> 187 | M26: =F26*I26 -> 0 | N26: =F26-K26-L26-M26 -> 1533.4
A27: Gatorade | B27: Halftime Presenting | C27: ='Broadcast Ad Sales Log'!J39 -> 1 | D27: ='Broadcast Ad Sales Log'!M39 -> 4000 | E27: ='Broadcast Ad Sales Log'!O39 -> 600 | F27: ='Broadcast Ad Sales Log'!P39 -> 3400 | G27: 0 | H27: 0.1 | I27: 0.02 | J27: =G27+H27+I27 -> 0.12 | K27: =F27*G27 -> 0 | L27: =F27*H27 -> 340 | M27: =F27*I27 -> 68 | N27: =F27-K27-L27-M27 -> 2992
A28: Verizon – feat. M. Osei #3 | B28: Player Mention | C28: ='Broadcast Ad Sales Log'!J42 -> 1 | D28: ='Broadcast Ad Sales Log'!M42 -> 2200 | E28: ='Broadcast Ad Sales Log'!O42 -> 330 | F28: ='Broadcast Ad Sales Log'!P42 -> 1870 | G28: 0.08 | H28: 0.1 | I28: 0 | J28: =G28+H28+I28 -> 0.18 | K28: =F28*G28 -> 149.6 | L28: =F28*H28 -> 187 | M28: =F28*I28 -> 0 | N28: =F28-K28-L28-M28 -> 1533.4
A29: TOTAL | C29: =SUM(C7:C28) -> 51 | D29: =SUM(D7:D28) -> 216900 | E29: =SUM(E7:E28) -> 42225 | F29: =SUM(F7:F28) -> 174675 | K29: =SUM(K7:K28) -> 2251.2 | L29: =SUM(L7:L28) -> 17467.5 | M29: =SUM(M7:M28) -> 692 | N29: =SUM(N7:N28) -> 154264.3

Sheet Revenue Distribution
A1: Club | B1: Metro United SC
A2: Game | B2: Metro United SC vs. Riverside City FC
A3: Period | B3: Single Game – 202x
A4: Purpose | B4: Revenue sharing – players, league, royalty holders
A6: A. PLAYER MENTION ROYALTIES
A7: Player | B7: Sponsors Featuring Player | C7: # Mentions (Spots) | D7: Net Revenue Attributable ($) | E7: Royalty Rate | F7: Royalty Amount ($) | G7: Payment Reference
A8: A. Rivera #10 | B8: Verizon (TV Pre+2H), Gatorade (TV 2H), State Farm (Radio 1H) | C8: ='Revenue by Sponsor Summary'!C11+'Revenue by Sponsor Summary'!C21+'Revenue by Sponsor Summary'!C26 -> 3 | D8: ='Revenue by Sponsor Summary'!F11+'Revenue by Sponsor Summary'!F21+'Revenue by Sponsor Summary'!F26 -> 11230 | E8: 0.08 | F8: =D8*E8 -> 898.4 | G8: PAY-PLY-001
A9: J. Thompson #7 | B9: State Farm (TV 1H), Nike (TV Post) | C9: ='Revenue by Sponsor Summary'!C15+'Revenue by Sponsor Summary'!C24 -> 2 | D9: ='Revenue by Sponsor Summary'!F15+'Revenue by Sponsor Summary'!F24 -> 9600 | E9: 0.08 | F9: =D9*E9 -> 768 | G9: PAY-PLY-002
A10: M. Osei #3 | B10: Nike (TV HT), Verizon (Radio 2H) | C10: ='Revenue by Sponsor Summary'!C19+'Revenue by Sponsor Summary'!C28 -> 2 | D10: ='Revenue by Sponsor Summary'!F19+'Revenue by Sponsor Summary'!F28 -> 7310 | E10: 0.08 | F10: =D10*E10 -> 584.8 | G10: PAY-PLY-003
A11: TOTAL | C11: =SUM(C8:C10) -> 7 | E11: =SUM(D8:D10) -> 28140 | F11: =SUM(F8:F10) -> 2251.2
A13: B. LEAGUE REVENUE SHARE (Per Collective Bargaining Agreement)
A14: League / Body | B14: Basis | C14: Total Net Revenue to Club ($) | D14: League Share Rate | E14: League Share ($) | F14: Payment Reference | G14: Notes
A15: National League Office | B15: Broadcast Ad Revenue CBA Mandate | C15: ='Revenue by Sponsor Summary'!F29 -> 174675 | D15: 0.1 | E15: =C15*D15 -> 17467.5 | F15: PAY-LGE-001 | G15: Remitted quarterly
A16: TOTAL | C16: =C15 -> 174675 | E16: =E15 -> 17467.5
A18: C. MUSIC & IP ROYALTY PAYMENTS (Broadcast Licensing)
A19: Rights Holder / Body | B19: Coverage | C19: Net Revenue Attributable ($) | D19: Royalty Rate | E19: Royalty Amount ($) | F19: Payment Reference | G19: Notes
A20: ASCAP / BMI | B20: Background & walk-up music in sponsored segments | C20: ='Revenue by Sponsor Summary'!F9+'Revenue by Sponsor Summary'!F17+'Revenue by Sponsor Summary'!F23+'Revenue by Sponsor Summary'!F27 -> 34600 | D20: 0.02 | E20: =C20*D20 -> 692 | F20: PAY-MUS-001 | G20: Per blanket license agreement
A21: TOTAL | C21: =C20 -> 34600 | E21: =E20 -> 692
A23: D. CLUB NET REVENUE WATERFALL
A24: Revenue / Deduction Component | B24: Amount ($) | C24: % of Gross | D24: Notes
A25: (+) Gross Ad Revenue | B25: ='Revenue by Sponsor Summary'!D29 -> 216900 | C25: =B25/B25 -> 1 | D25: Per broadcaster invoice
A26: (-) Broadcaster Commission | B26: =-'Revenue by Sponsor Summary'!E29 -> -42225 | C26: =B26/B25 -> -0.19467497 | D26: TV 20% / Radio 15%
A27: (-) Player Mention Royalties | B27: =-F11 -> -2251.2 | C27: =B27/B25 -> -0.010378976 | D27: 8% on player mention net revenue
A28: (-) League Revenue Share | B28: =-E15 -> -17467.5 | C28: =B28/B25 -> -0.080532503 | D28: 10% per CBA
A29: (-) Music & IP Royalties | B29: =-E20 -> -692 | C29: =B29/B25 -> -0.0031904103 | D29: 2% on applicable segments
A30: = Club Net Revenue | B30: =B25+B26+B27+B28+B29 -> 154264.3 | C30: =B30/B25 -> 0.71122314 | D30: Available for club operations
