Workbook

Sheet Ticket Sales Log
A1: Club | B1: Metro United SC
A2: Opponent | B2: Riverside City FC
A3: Game Date | B3: TBD, 202x
A4: Venue | B4: Metro Arena (Capacity: 25,000)
A5: Report Period | B5: All sales from Early Bird open through Gate (≤30 min before KO)
A6: Currency | B6: USD ($)
A7: Prepared By | B7: Ticketing Operations Dept
A9: Sale ID | B9: Channel | C9: Member Type | D9: Timing Tier | E9: Days Before Game | F9: Ticket Category | G9: Zone / Section | H9: Base Price ($) | I9: Tier Multiplier | J9: Member Discount | K9: Sale Price ($) | L9: Qty Sold | M9: Gross Revenue ($) | N9: Seller Comm % | O9: Seller Comm ($) | P9: Net Revenue to Pool ($)
A10: TKT-001 | B10: Online | C10: Member | D10: Early Bird | E10: 60–90 | F10: VIP Suite Box | G10: Suites Level 1 | H10: 350 | I10: 0.8 | J10: 0.12 | K10: =H10*I10*(1-J10) -> 246.4 | L10: 18 | M10: =K10*L10 -> 4435.2 | N10: 0.08 | O10: =M10*N10 -> 354.816 | P10: =M10-O10 -> 4080.384
A11: TKT-002 | B11: Online | C11: Member | D11: Early Bird | E11: 60–90 | F11: Club / Premium | G11: Club Level 100s | H11: 185 | I11: 0.8 | J11: 0.12 | K11: =H11*I11*(1-J11) -> 130.24 | L11: 95 | M11: =K11*L11 -> 12372.8 | N11: 0.08 | O11: =M11*N11 -> 989.824 | P11: =M11-O11 -> 11382.976
A12: TKT-003 | B12: Online | C12: Member | D12: Early Bird | E12: 60–90 | F12: Lower Bowl | G12: Sections 200–230 | H12: 95 | I12: 0.8 | J12: 0.12 | K12: =H12*I12*(1-J12) -> 66.88 | L12: 210 | M12: =K12*L12 -> 14044.8 | N12: 0.08 | O12: =M12*N12 -> 1123.584 | P12: =M12-O12 -> 12921.216
A13: TKT-004 | B13: Online | C13: Member | D13: Advance | E13: 30–59 | F13: Club / Premium | G13: Club Level 100s | H13: 185 | I13: 0.9 | J13: 0.12 | K13: =H13*I13*(1-J13) -> 146.52 | L13: 140 | M13: =K13*L13 -> 20512.8 | N13: 0.08 | O13: =M13*N13 -> 1641.024 | P13: =M13-O13 -> 18871.776
A14: TKT-005 | B14: Online | C14: Member | D14: Advance | E14: 30–59 | F14: Lower Bowl | G14: Sections 200–230 | H14: 95 | I14: 0.9 | J14: 0.12 | K14: =H14*I14*(1-J14) -> 75.24 | L14: 280 | M14: =K14*L14 -> 21067.2 | N14: 0.08 | O14: =M14*N14 -> 1685.376 | P14: =M14-O14 -> 19381.824
A15: TKT-006 | B15: Online | C15: Member | D15: Advance | E15: 30–59 | F15: Upper Bowl | G15: Sections 300–340 | H15: 55 | I15: 0.9 | J15: 0.12 | K15: =H15*I15*(1-J15) -> 43.56 | L15: 320 | M15: =K15*L15 -> 13939.2 | N15: 0.08 | O15: =M15*N15 -> 1115.136 | P15: =M15-O15 -> 12824.064
A16: TKT-007 | B16: Online | C16: Member | D16: Standard | E16: 14–29 | F16: Club / Premium | G16: Club Level 100s | H16: 185 | I16: 1 | J16: 0.12 | K16: =H16*I16*(1-J16) -> 162.8 | L16: 180 | M16: =K16*L16 -> 29304 | N16: 0.1 | O16: =M16*N16 -> 2930.4 | P16: =M16-O16 -> 26373.6
A17: TKT-008 | B17: Online | C17: Member | D17: Standard | E17: 14–29 | F17: Lower Bowl | G17: Sections 200–230 | H17: 95 | I17: 1 | J17: 0.12 | K17: =H17*I17*(1-J17) -> 83.6 | L17: 350 | M17: =K17*L17 -> 29260 | N17: 0.1 | O17: =M17*N17 -> 2926 | P17: =M17-O17 -> 26334
A18: TKT-009 | B18: Online | C18: Member | D18: Standard | E18: 14–29 | F18: Upper Bowl | G18: Sections 300–340 | H18: 55 | I18: 1 | J18: 0.12 | K18: =H18*I18*(1-J18) -> 48.4 | L18: 420 | M18: =K18*L18 -> 20328 | N18: 0.1 | O18: =M18*N18 -> 2032.8 | P18: =M18-O18 -> 18295.2
A19: TKT-010 | B19: Online | C19: Member | D19: Late | E19: 7–13 | F19: Lower Bowl | G19: Sections 200–230 | H19: 95 | I19: 1.1 | J19: 0.12 | K19: =H19*I19*(1-J19) -> 91.96 | L19: 190 | M19: =K19*L19 -> 17472.4 | N19: 0.1 | O19: =M19*N19 -> 1747.24 | P19: =M19-O19 -> 15725.16
A20: TKT-011 | B20: Online | C20: Member | D20: Late | E20: 7–13 | F20: Upper Bowl | G20: Sections 300–340 | H20: 55 | I20: 1.1 | J20: 0.12 | K20: =H20*I20*(1-J20) -> 53.24 | L20: 240 | M20: =K20*L20 -> 12777.6 | N20: 0.1 | O20: =M20*N20 -> 1277.76 | P20: =M20-O20 -> 11499.84
A21: TKT-012 | B21: Online | C21: Member | D21: Last Minute | E21: 2–6 | F21: Upper Bowl | G21: Sections 300–340 | H21: 55 | I21: 1.2 | J21: 0.12 | K21: =H21*I21*(1-J21) -> 58.08 | L21: 80 | M21: =K21*L21 -> 4646.4 | N21: 0.12 | O21: =M21*N21 -> 557.568 | P21: =M21-O21 -> 4088.832
... A93: TKT-084 | B93: Onsite | C93: Non-Member | D93: Gate | E93: ≤ 30 min | F93: General Admission | G93: GA Terrace | H93: 35 | I93: 1.5 | J93: 0 | K93: =H93*I93*(1-J93) -> 52.5 | L93: 190 | M93: =K93*L93 -> 9975 | N93: 0.05 | O93: =M93*N93 -> 498.75 | P93: =M93-O93 -> 9476.25
A94: TOTAL | L94: =SUM(L10:L93) -> 18355 | M94: =SUM(M10:M93) -> 1156451.1 | O94: =SUM(O10:O93) -> 90127.722 | P94: =SUM(P10:P93) -> 1066323.4
A95: Online Sub-Total | L95: =L10+L11+L12+L13+L14+L15+L16+L17+L18+L19+L20+L21+L22+L23+L24+L25+L26+L27+L28+L29+L30+L31+L32+L33+L34+L35+L36+L37+L38+L39+L40+L41+L42+L43+L44 -> 8775 | M95: =M10+M11+M12+M13+M14+M15+M16+M17+M18+M19+M20+M21+M22+M23+M24+M25+M26+M27+M28+M29+M30+M31+M32+M33+M34+M35+M36+M37+M38+M39+M40+M41+M42+M43+M44 -> 584948.2 | O95: =O10+O11+O12+O13+O14+O15+O16+O17+O18+O19+O20+O21+O22+O23+O24+O25+O26+O27+O28+O29+O30+O31+O32+O33+O34+O35+O36+O37+O38+O39+O40+O41+O42+O43+O44 -> 55283.164 | P95: =P10+P11+P12+P13+P14+P15+P16+P17+P18+P19+P20+P21+P22+P23+P24+P25+P26+P27+P28+P29+P30+P31+P32+P33+P34+P35+P36+P37+P38+P39+P40+P41+P42+P43+P44 -> 529665.04
A96: App Sub-Total | L96: =L45+L46+L47+L48+L49+L50+L51+L52+L53+L54+L55+L56+L57+L58+L59+L60+L61+L62+L63+L64+L65+L66+L67+L68+L69+L70+L71 -> 6955 | M96: =M45+M46+M47+M48+M49+M50+M51+M52+M53+M54+M55+M56+M57+M58+M59+M60+M61+M62+M63+M64+M65+M66+M67+M68+M69+M70+M71 -> 412566.55 | O96: =O45+O46+O47+O48+O49+O50+O51+O52+O53+O54+O55+O56+O57+O58+O59+O60+O61+O62+O63+O64+O65+O66+O67+O68+O69+O70+O71 -> 27906.776 | P96: =P45+P46+P47+P48+P49+P50+P51+P52+P53+P54+P55+P56+P57+P58+P59+P60+P61+P62+P63+P64+P65+P66+P67+P68+P69+P70+P71 -> 384659.77
A97: Onsite Sub-Total | L97: =L72+L73+L74+L75+L76+L77+L78+L79+L80+L81+L82+L83+L84+L85+L86+L87+L88+L89+L90+L91+L92+L93 -> 2625 | M97: =M72+M73+M74+M75+M76+M77+M78+M79+M80+M81+M82+M83+M84+M85+M86+M87+M88+M89+M90+M91+M92+M93 -> 158936.35 | O97: =O72+O73+O74+O75+O76+O77+O78+O79+O80+O81+O82+O83+O84+O85+O86+O87+O88+O89+O90+O91+O92+O93 -> 6937.7815 | P97: =P72+P73+P74+P75+P76+P77+P78+P79+P80+P81+P82+P83+P84+P85+P86+P87+P88+P89+P90+P91+P92+P93 -> 151998.57

Sheet Revenue by Channel & Tier
A1: Club | B1: Metro United SC
A2: Opponent | B2: Riverside City FC
A3: Game Date | B3: TBD, 202x
A4: Purpose | B4: Revenue summary by seller channel and sale timing tier
A6: Channel | B6: Timing Tier | C6: Days Before Game | D6: Seller Comm Rate | E6: Tickets Sold | F6: Avg. Sale Price ($) | G6: Gross Revenue ($) | H6: Seller Comm ($) | I6: Net Revenue to Pool ($) | J6: Net as % of Gross
A7: Online | B7: Early Bird | C7: 60–90 | D7: 0.08 | E7: ='Ticket Sales Log'!L10+'Ticket Sales Log'!L11+'Ticket Sales Log'!L12+'Ticket Sales Log'!L23+'Ticket Sales Log'!L24+'Ticket Sales Log'!L25 -> 1413 | F7: =IF(G7>0,G7/E7,0) -> 53.96518 | G7: ='Ticket Sales Log'!M10+'Ticket Sales Log'!M11+'Ticket Sales Log'!M12+'Ticket Sales Log'!M23+'Ticket Sales Log'!M24+'Ticket Sales Log'!M25 -> 76252.8 | H7: ='Ticket Sales Log'!O10+'Ticket Sales Log'!O11+'Ticket Sales Log'!O12+'Ticket Sales Log'!O23+'Ticket Sales Log'!O24+'Ticket Sales Log'!O25 -> 6100.224 | I7: ='Ticket Sales Log'!P10+'Ticket Sales Log'!P11+'Ticket Sales Log'!P12+'Ticket Sales Log'!P23+'Ticket Sales Log'!P24+'Ticket Sales Log'!P25 -> 70152.576 | J7: =IF(G7>0,I7/G7,0) -> 0.92
A8: Online | B8: Advance | C8: 30–59 | D8: 0.08 | E8: ='Ticket Sales Log'!L13+'Ticket Sales Log'!L14+'Ticket Sales Log'!L15+'Ticket Sales Log'!L26+'Ticket Sales Log'!L27+'Ticket Sales Log'!L28+'Ticket Sales Log'!L29 -> 2192 | F8: =IF(G8>0,G8/E8,0) -> 59.324453 | G8: ='Ticket Sales Log'!M13+'Ticket Sales Log'!M14+'Ticket Sales Log'!M15+'Ticket Sales Log'!M26+'Ticket Sales Log'!M27+'Ticket Sales Log'!M28+'Ticket Sales Log'!M29 -> 130039.2 | H8: ='Ticket Sales Log'!O13+'Ticket Sales Log'!O14+'Ticket Sales Log'!O15+'Ticket Sales Log'!O26+'Ticket Sales Log'!O27+'Ticket Sales Log'!O28+'Ticket Sales Log'!O29 -> 10403.136 | I8: ='Ticket Sales Log'!P13+'Ticket Sales Log'!P14+'Ticket Sales Log'!P15+'Ticket Sales Log'!P26+'Ticket Sales Log'!P27+'Ticket Sales Log'!P28+'Ticket Sales Log'!P29 -> 119636.06 | J8: =IF(G8>0,I8/G8,0) -> 0.92
A9: Online | B9: Standard | C9: 14–29 | D9: 0.1 | E9: ='Ticket Sales Log'!L16+'Ticket Sales Log'!L17+'Ticket Sales Log'!L18+'Ticket Sales Log'!L30+'Ticket Sales Log'!L31+'Ticket Sales Log'!L32+'Ticket Sales Log'!L33+'Ticket Sales Log'!L34+'Ticket Sales Log'!L35 -> 3080 | F9: =IF(G9>0,G9/E9,0) -> 73.617532 | G9: ='Ticket Sales Log'!M16+'Ticket Sales Log'!M17+'Ticket Sales Log'!M18+'Ticket Sales Log'!M30+'Ticket Sales Log'!M31+'Ticket Sales Log'!M32+'Ticket Sales Log'!M33+'Ticket Sales Log'!M34+'Ticket Sales Log'!M35 -> 226742 | H9: ='Ticket Sales Log'!O16+'Ticket Sales Log'!O17+'Ticket Sales Log'!O18+'Ticket Sales Log'!O30+'Ticket Sales Log'!O31+'Ticket Sales Log'!O32+'Ticket Sales Log'!O33+'Ticket Sales Log'!O34+'Ticket Sales Log'!O35 -> 22674.2 | I9: ='Ticket Sales Log'!P16+'Ticket Sales Log'!P17+'Ticket Sales Log'!P18+'Ticket Sales Log'!P30+'Ticket Sales Log'!P31+'Ticket Sales Log'!P32+'Ticket Sales Log'!P33+'Ticket Sales Log'!P34+'Ticket Sales Log'!P35 -> 204067.8 | J9: =IF(G9>0,I9/G9,0) -> 0.9
A10: Online | B10: Late | C10: 7–13 | D10: 0.1 | E10: ='Ticket Sales Log'!L19+'Ticket Sales Log'!L20+'Ticket Sales Log'!L36+'Ticket Sales Log'!L37+'Ticket Sales Log'!L38+'Ticket Sales Log'!L39 -> 1360 | F10: =IF(G10>0,G10/E10,0) -> 78.091912 | G10: ='Ticket Sales Log'!M19+'Ticket Sales Log'!M20+'Ticket Sales Log'!M36+'Ticket Sales Log'!M37+'Ticket Sales Log'!M38+'Ticket Sales Log'!M39 -> 106205 | H10: ='Ticket Sales Log'!O19+'Ticket Sales Log'!O20+'Ticket Sales Log'!O36+'Ticket Sales Log'!O37+'Ticket Sales Log'!O38+'Ticket Sales Log'!O39 -> 10620.5 | I10: ='Ticket Sales Log'!P19+'Ticket Sales Log'!P20+'Ticket Sales Log'!P36+'Ticket Sales Log'!P37+'Ticket Sales Log'!P38+'Ticket Sales Log'!P39 -> 95584.5 | J10: =IF(G10>0,I10/G10,0) -> 0.9
A11: Online | B11: Last Minute | C11: 2–6 | D11: 0.12 | E11: ='Ticket Sales Log'!L21+'Ticket Sales Log'!L40+'Ticket Sales Log'!L41+'Ticket Sales Log'!L42 -> 515 | F11: =IF(G11>0,G11/E11,0) -> 64.303689 | G11: ='Ticket Sales Log'!M21+'Ticket Sales Log'!M40+'Ticket Sales Log'!M41+'Ticket Sales Log'!M42 -> 33116.4 | H11: ='Ticket Sales Log'!O21+'Ticket Sales Log'!O40+'Ticket Sales Log'!O41+'Ticket Sales Log'!O42 -> 3973.968 | I11: ='Ticket Sales Log'!P21+'Ticket Sales Log'!P40+'Ticket Sales Log'!P41+'Ticket Sales Log'!P42 -> 29142.432 | J11: =IF(G11>0,I11/G11,0) -> 0.88
A12: Online | B12: Day Of Game | C12: Same day >30m | D12: 0.12 | E12: ='Ticket Sales Log'!L22+'Ticket Sales Log'!L43+'Ticket Sales Log'!L44 -> 215 | F12: =IF(G12>0,G12/E12,0) -> 58.571163 | G12: ='Ticket Sales Log'!M22+'Ticket Sales Log'!M43+'Ticket Sales Log'!M44 -> 12592.8 | H12: ='Ticket Sales Log'!O22+'Ticket Sales Log'!O43+'Ticket Sales Log'!O44 -> 1511.136 | I12: ='Ticket Sales Log'!P22+'Ticket Sales Log'!P43+'Ticket Sales Log'!P44 -> 11081.664 | J12: =IF(G12>0,I12/G12,0) -> 0.88
A13: App | B13: Early Bird | C13: 60–90 | D13: 0.06 | E13: ='Ticket Sales Log'!L45+'Ticket Sales Log'!L46+'Ticket Sales Log'!L55+'Ticket Sales Log'!L56+'Ticket Sales Log'!L57 -> 1145 | F13: =IF(G13>0,G13/E13,0) -> 51.286638 | G13: ='Ticket Sales Log'!M45+'Ticket Sales Log'!M46+'Ticket Sales Log'!M55+'Ticket Sales Log'!M56+'Ticket Sales Log'!M57 -> 58723.2 | H13: ='Ticket Sales Log'!O45+'Ticket Sales Log'!O46+'Ticket Sales Log'!O55+'Ticket Sales Log'!O56+'Ticket Sales Log'!O57 -> 3523.392 | I13: ='Ticket Sales Log'!P45+'Ticket Sales Log'!P46+'Ticket Sales Log'!P55+'Ticket Sales Log'!P56+'Ticket Sales Log'!P57 -> 55199.808 | J13: =IF(G13>0,I13/G13,0) -> 0.94
A14: App | B14: Advance | C14: 30–59 | D14: 0.06 | E14: ='Ticket Sales Log'!L47+'Ticket Sales Log'!L48+'Ticket Sales Log'!L58+'Ticket Sales Log'!L59+'Ticket Sales Log'!L60 -> 1755 | F14: =IF(G14>0,G14/E14,0) -> 51.730769 | G14: ='Ticket Sales Log'!M47+'Ticket Sales Log'!M48+'Ticket Sales Log'!M58+'Ticket Sales Log'!M59+'Ticket Sales Log'!M60 -> 90787.5 | H14: ='Ticket Sales Log'!O47+'Ticket Sales Log'!O48+'Ticket Sales Log'!O58+'Ticket Sales Log'!O59+'Ticket Sales Log'!O60 -> 5447.25 | I14: ='Ticket Sales Log'!P47+'Ticket Sales Log'!P48+'Ticket Sales Log'!P58+'Ticket Sales Log'!P59+'Ticket Sales Log'!P60 -> 85340.25 | J14: =IF(G14>0,I14/G14,0) -> 0.94
A15: App | B15: Standard | C15: 14–29 | D15: 0.07 | E15: ='Ticket Sales Log'!L49+'Ticket Sales Log'!L50+'Ticket Sales Log'!L61+'Ticket Sales Log'!L62+'Ticket Sales Log'!L63+'Ticket Sales Log'!L64+'Ticket Sales Log'!L65 -> 2490 | F15: =IF(G15>0,G15/E15,0) -> 66.308434 | G15: ='Ticket Sales Log'!M49+'Ticket Sales Log'!M50+'Ticket Sales Log'!M61+'Ticket Sales Log'!M62+'Ticket Sales Log'!M63+'Ticket Sales Log'!M64+'Ticket Sales Log'!M65 -> 165108 | H15: ='Ticket Sales Log'!O49+'Ticket Sales Log'!O50+'Ticket Sales Log'!O61+'Ticket Sales Log'!O62+'Ticket Sales Log'!O63+'Ticket Sales Log'!O64+'Ticket Sales Log'!O65 -> 11557.56 | I15: ='Ticket Sales Log'!P49+'Ticket Sales Log'!P50+'Ticket Sales Log'!P61+'Ticket Sales Log'!P62+'Ticket Sales Log'!P63+'Ticket Sales Log'!P64+'Ticket Sales Log'!P65 -> 153550.44 | J15: =IF(G15>0,I15/G15,0) -> 0.93
A16: App | B16: Late | C16: 7–13 | D16: 0.07 | E16: ='Ticket Sales Log'!L51+'Ticket Sales Log'!L52+'Ticket Sales Log'!L66+'Ticket Sales Log'!L67+'Ticket Sales Log'!L68 -> 1070 | F16: =IF(G16>0,G16/E16,0) -> 67.137009 | G16: ='Ticket Sales Log'!M51+'Ticket Sales Log'!M52+'Ticket Sales Log'!M66+'Ticket Sales Log'!M67+'Ticket Sales Log'!M68 -> 71836.6 | H16: ='Ticket Sales Log'!O51+'Ticket Sales Log'!O52+'Ticket Sales Log'!O66+'Ticket Sales Log'!O67+'Ticket Sales Log'!O68 -> 5028.562 | I16: ='Ticket Sales Log'!P51+'Ticket Sales Log'!P52+'Ticket Sales Log'!P66+'Ticket Sales Log'!P67+'Ticket Sales Log'!P68 -> 66808.038 | J16: =IF(G16>0,I16/G16,0) -> 0.93
A17: App | B17: Last Minute | C17: 2–6 | D17: 0.09 | E17: ='Ticket Sales Log'!L53+'Ticket Sales Log'!L69+'Ticket Sales Log'!L70 -> 365 | F17: =IF(G17>0,G17/E17,0) -> 52.974247 | G17: ='Ticket Sales Log'!M53+'Ticket Sales Log'!M69+'Ticket Sales Log'!M70 -> 19335.6 | H17: ='Ticket Sales Log'!O53+'Ticket Sales Log'!O69+'Ticket Sales Log'!O70 -> 1740.204 | I17: ='Ticket Sales Log'!P53+'Ticket Sales Log'!P69+'Ticket Sales Log'!P70 -> 17595.396 | J17: =IF(G17>0,I17/G17,0) -> 0.91
A18: App | B18: Day Of Game | C18: Same day >30m | D18: 0.09 | E18: ='Ticket Sales Log'!L54+'Ticket Sales Log'!L71 -> 130 | F18: =IF(G18>0,G18/E18,0) -> 52.120385 | G18: ='Ticket Sales Log'!M54+'Ticket Sales Log'!M71 -> 6775.65 | H18: ='Ticket Sales Log'!O54+'Ticket Sales Log'!O71 -> 609.8085 | I18: ='Ticket Sales Log'!P54+'Ticket Sales Log'!P71 -> 6165.8415 | J18: =IF(G18>0,I18/G18,0) -> 0.91
A19: Onsite | B19: Standard | C19: 14–29 | D19: 0.04 | E19: ='Ticket Sales Log'!L72+'Ticket Sales Log'!L73+'Ticket Sales Log'!L79+'Ticket Sales Log'!L80+'Ticket Sales Log'!L81+'Ticket Sales Log'!L82+'Ticket Sales Log'!L83 -> 1080 | F19: =IF(G19>0,G19/E19,0) -> 60.77963 | G19: ='Ticket Sales Log'!M72+'Ticket Sales Log'!M73+'Ticket Sales Log'!M79+'Ticket Sales Log'!M80+'Ticket Sales Log'!M81+'Ticket Sales Log'!M82+'Ticket Sales Log'!M83 -> 65642 | H19: ='Ticket Sales Log'!O72+'Ticket Sales Log'!O73+'Ticket Sales Log'!O79+'Ticket Sales Log'!O80+'Ticket Sales Log'!O81+'Ticket Sales Log'!O82+'Ticket Sales Log'!O83 -> 2625.68 | I19: ='Ticket Sales Log'!P72+'Ticket Sales Log'!P73+'Ticket Sales Log'!P79+'Ticket Sales Log'!P80+'Ticket Sales Log'!P81+'Ticket Sales Log'!P82+'Ticket Sales Log'!P83 -> 63016.32 | J19: =IF(G19>0,I19/G19,0) -> 0.96
A20: Onsite | B20: Late | C20: 7–13 | D20: 0.04 | E20: ='Ticket Sales Log'!L74+'Ticket Sales Log'!L84+'Ticket Sales Log'!L85+'Ticket Sales Log'!L86 -> 590 | F20: =IF(G20>0,G20/E20,0) -> 59.765424 | G20: ='Ticket Sales Log'!M74+'Ticket Sales Log'!M84+'Ticket Sales Log'!M85+'Ticket Sales Log'!M86 -> 35261.6 | H20: ='Ticket Sales Log'!O74+'Ticket Sales Log'!O84+'Ticket Sales Log'!O85+'Ticket Sales Log'!O86 -> 1410.464 | I20: ='Ticket Sales Log'!P74+'Ticket Sales Log'!P84+'Ticket Sales Log'!P85+'Ticket Sales Log'!P86 -> 33851.136 | J20: =IF(G20>0,I20/G20,0) -> 0.96
A21: Onsite | B21: Last Minute | C21: 2–6 | D21: 0.05 | E21: ='Ticket Sales Log'!L75+'Ticket Sales Log'!L87+'Ticket Sales Log'!L88+'Ticket Sales Log'!L89 -> 385 | F21: =IF(G21>0,G21/E21,0) -> 62.375065 | G21: ='Ticket Sales Log'!M75+'Ticket Sales Log'!M87+'Ticket Sales Log'!M88+'Ticket Sales Log'!M89 -> 24014.4 | H21: ='Ticket Sales Log'!O75+'Ticket Sales Log'!O87+'Ticket Sales Log'!O88+'Ticket Sales Log'!O89 -> 1200.72 | I21: ='Ticket Sales Log'!P75+'Ticket Sales Log'!P87+'Ticket Sales Log'!P88+'Ticket Sales Log'!P89 -> 22813.68 | J21: =IF(G21>0,I21/G21,0) -> 0.95
A22: Onsite | B22: Day Of Game | C22: Same day >30m | D22: 0.05 | E22: ='Ticket Sales Log'!L76+'Ticket Sales Log'!L90+'Ticket Sales Log'!L91 -> 255 | F22: =IF(G22>0,G22/E22,0) -> 59.087647 | G22: ='Ticket Sales Log'!M76+'Ticket Sales Log'!M90+'Ticket Sales Log'!M91 -> 15067.35 | H22: ='Ticket Sales Log'!O76+'Ticket Sales Log'!O90+'Ticket Sales Log'!O91 -> 753.3675 | I22: ='Ticket Sales Log'!P76+'Ticket Sales Log'!P90+'Ticket Sales Log'!P91 -> 14313.983 | J22: =IF(G22>0,I22/G22,0) -> 0.95
A23: Onsite | B23: Gate | C23: ≤ 30 min | D23: 0.05 | E23: ='Ticket Sales Log'!L77+'Ticket Sales Log'!L78+'Ticket Sales Log'!L92+'Ticket Sales Log'!L93 -> 315 | F23: =IF(G23>0,G23/E23,0) -> 60.161905 | G23: ='Ticket Sales Log'!M77+'Ticket Sales Log'!M78+'Ticket Sales Log'!M92+'Ticket Sales Log'!M93 -> 18951 | H23: ='Ticket Sales Log'!O77+'Ticket Sales Log'!O78+'Ticket Sales Log'!O92+'Ticket Sales Log'!O93 -> 947.55 | I23: ='Ticket Sales Log'!P77+'Ticket Sales Log'!P78+'Ticket Sales Log'!P92+'Ticket Sales Log'!P93 -> 18003.45 | J23: =IF(G23>0,I23/G23,0) -> 0.95
A24: GRAND TOTAL | E24: =SUM(E7:E23) -> 18355 | F24: =IF(G24>0,G24/E24,0) -> 63.004691 | G24: =SUM(G7:G23) -> 1156451.1 | H24: =SUM(H7:H23) -> 90127.722 | I24: =SUM(I7:I23) -> 1066323.4 | J24: =IF(G24>0,I24/G24,0) -> 0.92206525
A25: Online Total | E25: =E7+E8+E9+E10+E11+E12 -> 8775 | F25: =IF((E7+E8+E9+E10+E11+E12)>0,(G7+G8+G9+G10+G11+G12)/(E7+E8+E9+E10+E11+E12),0) -> 66.660764 | G25: =G7+G8+G9+G10+G11+G12 -> 584948.2 | H25: =H7+H8+H9+H10+H11+H12 -> 55283.164 | I25: =I7+I8+I9+I10+I11+I12 -> 529665.04 | J25: =IF((G7+G8+G9+G10+G11+G12)>0,(I7+I8+I9+I10+I11+I12)/(G7+G8+G9+G10+G11+G12),0) -> 0.9054905
A26: App Total | E26: =E13+E14+E15+E16+E17+E18 -> 6955 | F26: =IF((E13+E14+E15+E16+E17+E18)>0,(G13+G14+G15+G16+G17+G18)/(E13+E14+E15+E16+E17+E18),0) -> 59.319418 | G26: =G13+G14+G15+G16+G17+G18 -> 412566.55 | H26: =H13+H14+H15+H16+H17+H18 -> 27906.777 | I26: =I13+I14+I15+I16+I17+I18 -> 384659.77 | J26: =IF((G13+G14+G15+G16+G17+G18)>0,(I13+I14+I15+I16+I17+I18)/(G13+G14+G15+G16+G17+G18),0) -> 0.93235812
A27: Onsite Total | E27: =E19+E20+E21+E22+E23 -> 2625 | F27: =IF((E19+E20+E21+E22+E23)>0,(G19+G20+G21+G22+G23)/(E19+E20+E21+E22+E23),0) -> 60.547181 | G27: =G19+G20+G21+G22+G23 -> 158936.35 | H27: =H19+H20+H21+H22+H23 -> 6937.7815 | I27: =I19+I20+I21+I22+I23 -> 151998.57 | J27: =IF((G19+G20+G21+G22+G23)>0,(I19+I20+I21+I22+I23)/(G19+G20+G21+G22+G23),0) -> 0.95634868

Sheet Revenue Distribution
A1: Club | B1: Metro United SC
A2: Opponent | B2: Riverside City FC
A3: Game Date | B3: TBD, 202x
A4: Purpose | B4: Revenue sharing – clubs, venue, league; commission summary by seller
A6: A. SELLER COMMISSION PAYABLE BY CHANNEL
A7: Channel | B7: Tickets Sold | C7: Gross Revenue ($) | D7: Avg Comm Rate | E7: Commission Payable ($) | F7: Net Revenue to Pool ($) | G7: Payment Reference
A8: Online | B8: ='Revenue by Channel & Tier'!E7+'Revenue by Channel & Tier'!E8+'Revenue by Channel & Tier'!E9+'Revenue by Channel & Tier'!E10+'Revenue by Channel & Tier'!E11+'Revenue by Channel & Tier'!E12 -> 8775 | C8: ='Revenue by Channel & Tier'!G7+'Revenue by Channel & Tier'!G8+'Revenue by Channel & Tier'!G9+'Revenue by Channel & Tier'!G10+'Revenue by Channel & Tier'!G11+'Revenue by Channel & Tier'!G12 -> 584948.2 | D8: =IF(C8>0,E8/C8,0) -> 0.094509504 | E8: ='Revenue by Channel & Tier'!H7+'Revenue by Channel & Tier'!H8+'Revenue by Channel & Tier'!H9+'Revenue by Channel & Tier'!H10+'Revenue by Channel & Tier'!H11+'Revenue by Channel & Tier'!H12 -> 55283.164 | F8: ='Revenue by Channel & Tier'!I7+'Revenue by Channel & Tier'!I8+'Revenue by Channel & Tier'!I9+'Revenue by Channel & Tier'!I10+'Revenue by Channel & Tier'!I11+'Revenue by Channel & Tier'!I12 -> 529665.04 | G8: PAY-OLN-001
A9: App | B9: ='Revenue by Channel & Tier'!E13+'Revenue by Channel & Tier'!E14+'Revenue by Channel & Tier'!E15+'Revenue by Channel & Tier'!E16+'Revenue by Channel & Tier'!E17+'Revenue by Channel & Tier'!E18 -> 6955 | C9: ='Revenue by Channel & Tier'!G13+'Revenue by Channel & Tier'!G14+'Revenue by Channel & Tier'!G15+'Revenue by Channel & Tier'!G16+'Revenue by Channel & Tier'!G17+'Revenue by Channel & Tier'!G18 -> 412566.55 | D9: =IF(C9>0,E9/C9,0) -> 0.067641879 | E9: ='Revenue by Channel & Tier'!H13+'Revenue by Channel & Tier'!H14+'Revenue by Channel & Tier'!H15+'Revenue by Channel & Tier'!H16+'Revenue by Channel & Tier'!H17+'Revenue by Channel & Tier'!H18 -> 27906.777 | F9: ='Revenue by Channel & Tier'!I13+'Revenue by Channel & Tier'!I14+'Revenue by Channel & Tier'!I15+'Revenue by Channel & Tier'!I16+'Revenue by Channel & Tier'!I17+'Revenue by Channel & Tier'!I18 -> 384659.77 | G9: PAY-APP-001
A10: Onsite | B10: ='Revenue by Channel & Tier'!E19+'Revenue by Channel & Tier'!E20+'Revenue by Channel & Tier'!E21+'Revenue by Channel & Tier'!E22+'Revenue by Channel & Tier'!E23 -> 2625 | C10: ='Revenue by Channel & Tier'!G19+'Revenue by Channel & Tier'!G20+'Revenue by Channel & Tier'!G21+'Revenue by Channel & Tier'!G22+'Revenue by Channel & Tier'!G23 -> 158936.35 | D10: =IF(C10>0,E10/C10,0) -> 0.04365132 | E10: ='Revenue by Channel & Tier'!H19+'Revenue by Channel & Tier'!H20+'Revenue by Channel & Tier'!H21+'Revenue by Channel & Tier'!H22+'Revenue by Channel & Tier'!H23 -> 6937.7815 | F10: ='Revenue by Channel & Tier'!I19+'Revenue by Channel & Tier'!I20+'Revenue by Channel & Tier'!I21+'Revenue by Channel & Tier'!I22+'Revenue by Channel & Tier'!I23 -> 151998.57 | G10: PAY-ONS-001
A11: TOTAL | B11: =SUM(B8:B10) -> 18355 | C11: =SUM(C8:C10) -> 1156451.1 | D11: =IF(C11>0,E11/C11,0) -> 0.077934745 | E11: =SUM(E8:E10) -> 90127.722 | F11: =SUM(F8:F10) -> 1066323.4
A13: B. REVENUE SHARING BETWEEN CLUBS
A14: Stakeholder | B14: Share % | C14: Net Revenue Pool ($) | D14: Share Amount ($) | E14: Running Club Net ($) | F14: Payment Reference | G14: Notes
A15: Home Club – Metro United SC | B15: 0.68 | C15: ='Revenue by Channel & Tier'!I24 -> 1066323.4 | D15: =C15*B15 -> 725099.9 | E15: =D15 -> 725099.9 | F15: PAY-HMC-001 | G15: Primary ticket revenue holder
A16: Away Club – Riverside City FC | B16: 0.18 | C16: ='Revenue by Channel & Tier'!I24 -> 1066323.4 | D16: =C16*B16 -> 191938.21 | E16: =E15-D16 -> 533161.69 | F16: PAY-AWY-001 | G16: Visiting team guarantee per league agreement
A17: Venue / Facility Fee | B17: 0.07 | C17: ='Revenue by Channel & Tier'!I24 -> 1066323.4 | D17: =C17*B17 -> 74642.636 | E17: =E16-D17 -> 458519.05 | F17: PAY-VEN-001 | G17: Arena ops, cleaning, security, infrastructure
A18: League Operations Fee | B18: 0.07 | C18: ='Revenue by Channel & Tier'!I24 -> 1066323.4 | D18: =C18*B18 -> 74642.636 | E18: =E17-D18 -> 383876.42 | F18: PAY-LGE-001 | G18: Per ticketing rights & league admin agreement
A19: TOTAL DISTRIBUTED | B19: =SUM(B15:B18) -> 1 | D19: =SUM(D15:D18) -> 1066323.4
A21: C. FULL REVENUE WATERFALL
A22: Revenue / Deduction Component | B22: Amount ($) | C22: % of Gross Revenue | D22: Notes
A23: (+) Gross Ticket Revenue | B23: ='Revenue by Channel & Tier'!G24 -> 1156451.1 | C23: =B23/B23 -> 1 | D23: Total across all channels & tiers
A24: (-) Online Seller Commission | B24: =-'Revenue by Channel & Tier'!H25 -> -55283.164 | C24: =B24/B23 -> -0.047804152 | D24: Avg 8–12% by timing tier
A25: (-) App Seller Commission | B25: =-'Revenue by Channel & Tier'!H26 -> -27906.777 | C25: =B25/B23 -> -0.024131393 | D25: Avg 6–9% by timing tier
A26: (-) Onsite Seller Commission | B26: =-'Revenue by Channel & Tier'!H27 -> -6937.7815 | C26: =B26/B23 -> -0.0059992001 | D26: Flat 4–5%
A27: =net revenue pool | B27: =B23+B24+B25+B26 -> 1066323.4 | C27: =B27/B23 -> 0.92206525 | D27: Available for club/venue/league distribution
A28: (-) Away Club Share (18%) | B28: =-D16 -> -191938.21 | C28: =B28/B23 -> -0.16597175 | D28: Riverside City FC guarantee
A29: (-) Venue / Facility Fee (7%) | B29: =-D17 -> -74642.636 | C29: =B29/B23 -> -0.064544568 | D29: Metro Arena operations
A30: (-) League Operations (7%) | B30: =-D18 -> -74642.636 | C30: =B30/B23 -> -0.064544568 | D30: League ticketing fee
A31: =home club net revenue | B31: =B27+B28+B29+B30 -> 725099.9 | C31: =B31/B23 -> 0.62700437 | D31: Metro United SC – retained revenue

Sheet Rate Card & Commission Rules
A1: Club | B1: Metro United SC
A2: Opponent | B2: Riverside City FC
A3: Game Date | B3: TBD, 202x
A4: Venue | B4: Metro Arena (Capacity: 25,000)
A5: Currency | B5: USD ($)
A7: A. TICKET BASE PRICES (Standard / Face Value)
A8: Category | B8: Zone / Section | C8: Base Price ($) | D8: Member Price ($) (12% off) | E8: Notes
A9: VIP Suite Box | B9: Suites Level 1 | C9: 350 | D9: =C9*(1-0.12) -> 308 | E9: Includes hospitality package
A10: Club / Premium | B10: Club Level 100s | C10: 185 | D10: =C10*(1-0.12) -> 162.8 | E10: Premium seating with lounge access
A11: Lower Bowl | B11: Sections 200–230 | C11: 95 | D11: =C11*(1-0.12) -> 83.6
A12: Upper Bowl | B12: Sections 300–340 | C12: 55 | D12: =C12*(1-0.12) -> 48.4
A13: General Admission | B13: GA Terrace | C13: 35 | D13: =C13*(1-0.12) -> 30.8 | E13: Standing / first-come
A14: Student / Youth | B14: Upper Bowl 350–360 | C14: 25 | D14: =C14*(1-0.12) -> 22 | E14: Valid student/youth ID required
A16: B. SALE TIMING TIERS (Price Multipliers Applied to Base Price)
A17: Timing Tier | B17: Days Before Game | C17: Price Multiplier | D17: Effect on Base Price | E17: Applies To | F17: Color Code
A18: Early Bird | B18: 60 – 90 days | C18: 0.8 | D18: 20% DISCOUNT | E18: Online, App
A19: Advance | B19: 30 – 59 days | C19: 0.9 | D19: 10% DISCOUNT | E19: Online, App
A20: Standard | B20: 14 – 29 days | C20: 1 | D20: Base price | E20: Online, App, Onsite
A21: Late | B21: 7 – 13 days | C21: 1.1 | D21: 10% PREMIUM | E21: Online, App, Onsite
A22: Last Minute | B22: 2 – 6 days | C22: 1.2 | D22: 20% PREMIUM | E22: Online, App, Onsite
A23: Day Of Game | B23: Same day >30m | C23: 1.35 | D23: 35% PREMIUM | E23: Online, App, Onsite
A24: Gate | B24: ≤ 30 min | C24: 1.5 | D24: 50% PREMIUM | E24: Onsite only
A26: C. SELLER CHANNEL COMMISSION RATES
A27: Channel | B27: Early Bird | C27: Advance | D27: Standard | E27: Late | F27: Last Minute / Day Of / Gate
A28: Online (Web) | B28: 0.08 | C28: 0.08 | D28: 0.1 | E28: 0.1 | F28: 0.12
A29: App (Mobile) | B29: 0.06 | C29: 0.06 | D29: 0.07 | E29: 0.07 | F29: 0.09
A30: Onsite Window | B30: N/A | C30: N/A | D30: 0.04 | E30: 0.04 | F30: 0.05
A32: D. REVENUE DISTRIBUTION (Applied to Net Revenue after Seller Commissions)
A33: Stakeholder | B33: Share % | C33: Basis | D33: Notes
A34: Home Club (Metro United SC) | B34: 0.68 | C34: Net Ticketing Revenue | D34: After all deductions
A35: Away Club (Riverside City FC) | B35: 0.18 | C35: Net Ticketing Revenue | D35: Visiting team guarantee
A36: Venue / Facility Fee | B36: 0.07 | C36: Net Ticketing Revenue | D36: Arena operations & maintenance
A37: League Operations Fee | B37: 0.07 | C37: Net Ticketing Revenue | D37: Per league ticketing agreement
